module_dependencies/__init__.py
module_dependencies/module/__init__.py
module_dependencies/module/module.py
module_dependencies/module/query.txt
module_dependencies/module/session.py
module_dependencies/source/__init__.py
module_dependencies/source/api.py
module_dependencies/source/factory.py
module_dependencies/source/source.py
module_dependencies/source/visitor.py
module_dependencies/util/__init__.py
module_dependencies/util/tokenize.py
module_dependencies-0.2.5.dist-info/LICENSE
module_dependencies-0.2.5.dist-info/METADATA
module_dependencies-0.2.5.dist-info/WHEEL
module_dependencies-0.2.5.dist-info/top_level.txt
module_dependencies-0.2.5.dist-info/RECORD
