Metadata-Version: 2.1
Name: module-dependencies
Version: 0.2.5
Summary: Gather module dependencies of source code
Home-page: https://github.com/tomaarsen/module_dependencies
Author: Tom Aarsen
Author-email: ta.aarsen@gmail.com
License: MIT
Project-URL: Documentation, https://tomaarsen.github.io/module_dependencies/
Project-URL: Source Code, https://github.com/tomaarsen/module_dependencies
Project-URL: Issue Tracker, https://github.com/tomaarsen/module_dependencies/issues
Platform: UNKNOWN
Classifier: License :: OSI Approved :: MIT License
Classifier: Programming Language :: Python
Classifier: Programming Language :: Python :: 3
Classifier: Programming Language :: Python :: 3.8
Classifier: Programming Language :: Python :: 3.9
Classifier: Programming Language :: Python :: 3.10
Classifier: Programming Language :: Python :: Implementation :: CPython
Classifier: Programming Language :: Python :: Implementation :: PyPy
Requires-Python: >=3.7
Requires-Dist: plotly
Requires-Dist: requests
Requires-Dist: tqdm
